rsyncdirector/__init__.py
rsyncdirector/main.py
rsyncdirector/lib/__init__.py
rsyncdirector/lib/command.py
rsyncdirector/lib/config.py
rsyncdirector/lib/enums.py
rsyncdirector/lib/envvars.py
rsyncdirector/lib/metrics.py
rsyncdirector/lib/pidfile.py
rsyncdirector/lib/rsync.py
rsyncdirector/lib/rsyncdirector.py
rsyncdirector/lib/utils.py
rsyncdirector-0.1.2.dist-info/LICENSE
rsyncdirector-0.1.2.dist-info/METADATA
rsyncdirector-0.1.2.dist-info/WHEEL
rsyncdirector-0.1.2.dist-info/entry_points.txt
rsyncdirector-0.1.2.dist-info/top_level.txt
rsyncdirector-0.1.2.dist-info/RECORD
