Metadata-Version: 2.2
Name: rsyncdirector
Version: 0.1.2
Summary: A tool to orchestrate rsyncing of data between multiple machines and instances of rsyncdirector
Author-email: Ryan Chapin <rchapin@nbinteractive.com>
License: This software is released under the Revised BSD License.
Project-URL: Homepage, https://github.com/rchapin/rsyncdirector
Project-URL: readme, https://github.com/rchapin/rsyncdirector/README.md
Classifier: Programming Language :: Python :: 3
Classifier: License :: OSI Approved :: BSD License
Classifier: Operating System :: POSIX :: Linux
Requires-Python: >=3.13
License-File: LICENSE
Requires-Dist: apscheduler==3.10.4
Requires-Dist: bcrypt==4.1.2
Requires-Dist: blinker==1.9.0
Requires-Dist: certifi==2025.1.31
Requires-Dist: cffi==1.17.0
Requires-Dist: charset-normalizer==3.4.1
Requires-Dist: click==8.1.8
Requires-Dist: cryptography==46.0.0
Requires-Dist: decorator==5.1.1
Requires-Dist: deprecated==1.2.14
Requires-Dist: fabric==3.2.2
Requires-Dist: flask==3.1.2
Requires-Dist: idna==3.10
Requires-Dist: invoke==2.2.0
Requires-Dist: itsdangerous==2.2.0
Requires-Dist: jinja2==3.1.6
Requires-Dist: markupsafe==3.0.2
Requires-Dist: paramiko==3.4.0
Requires-Dist: prometheus-client==0.21.1
Requires-Dist: psutil==7.1.3
Requires-Dist: pycparser==2.21
Requires-Dist: pynacl==1.5.0
Requires-Dist: pytz==2023.3.post1
Requires-Dist: pyyaml==6.0.1
Requires-Dist: requests==2.32.5
Requires-Dist: six==1.16.0
Requires-Dist: tzlocal==2.1
Requires-Dist: urllib3==2.6.3
Requires-Dist: werkzeug==3.1.5
Requires-Dist: wrapt==1.16.0
Provides-Extra: test
Requires-Dist: certifi==2025.1.31; extra == "test"
Requires-Dist: charset-normalizer==3.4.1; extra == "test"
Requires-Dist: coverage==7.4.0; extra == "test"
Requires-Dist: dataclass-wizard==0.35.1; extra == "test"
Requires-Dist: docker==7.1.0; extra == "test"
Requires-Dist: idna==3.10; extra == "test"
Requires-Dist: requests==2.32.5; extra == "test"
Requires-Dist: urllib3==2.6.3; extra == "test"
Provides-Extra: dev
Requires-Dist: setuptools==75.8.0; extra == "dev"
Requires-Dist: pip-tools; extra == "dev"
Requires-Dist: pkginfo; extra == "dev"
Requires-Dist: twine; extra == "dev"
Requires-Dist: pytest; extra == "dev"
Requires-Dist: safety; extra == "dev"
